{
  "1": {
    "119": [
      "毛坯"
    ],
    "120": [
      "是的"
    ],
    "124": [
      "万科云城"
    ],
    "125": [
      "深圳"
    ],
    "126": [
      "108"
    ],
    "127": [
      "可以"
    ],
    "128": [
      "许"
    ],
    "122": [
      "是的"
    ]
  },
  "2": {
    "119": [
      "毛坯"
    ],
    "120": [
      "年底"
    ],
    "123": [
      "收了"
    ],
    "124": [
      "万科云城"
    ],
    "125": [
      "深圳"
    ],
    "126": [
      "108"
    ],
    "127": [
      "可以"
    ],
    "128": [
      "许"
    ],
    "122": [
      "是的"
    ]
  }
}